vaip/__init__.py
vaip/helpers.py
vaip/ontology.py
vaip/session.py
vaip/sparql_utils.py
vaip/utils.py
vaip/data/skos-core.owl
vaip/data/vaip-core.owl
vaip/data/vaip-coreCombined.owl
vaip/data/vaip-framework.owl
vaip/data/shacl/vaip_core_shapes.shacl
vaip/documentation/README.md
vaip/documentation/utils.html
vaip/system/__init__.py
vaip/system/backend/__init__.py
vaip/system/backend/deploy_agents.py
vaip/system/backend/neptune.py
vaip/system/backend/trigger_agents.py
vaip/system/backend/utilities/__init__.py
vaip/system/backend/utilities/s3_helper.py
vaip/system/patterns/__init__.py
vaip/system/patterns/aic.py
vaip/system/patterns/pattern_metadata.py
vaip/system/patterns/process.py
vaip/system/patterns/session.py
vaip/system/patterns/task.py
ncap_vaip_api-0.67.0.dist-info/METADATA
ncap_vaip_api-0.67.0.dist-info/WHEEL
ncap_vaip_api-0.67.0.dist-info/licenses/LICENSE
ncap_vaip_api-0.67.0.dist-info/RECORD
