Metadata-Version: 2.1
Name: ncap-vaip-api
Version: 0.67.0
Summary: A package representing an API implementation of the vAIP ontology
Author-email: NCEI <ncap.support@noaa.gov>
License-File: LICENSE
Classifier: Development Status :: 4 - Beta
Classifier: Operating System :: OS Independent
Classifier: Programming Language :: Python :: 3
Requires-Python: >=3.6
